{
  "pools": [
    {
      "rolls": 1,
      "entries": [
        {
          "type": "minecraft:item",
          "name": "minecraft:experience_bottle",
          "functions": [
            {
              "function": "minecraft:set_count",
              "count": {
                "type": "minecraft:uniform",
                "min": 50,
                "max": 130
              }
            }
          ]
        }
      ]
    },
    {
      "rolls": 1,
      "entries": [
        {
          "type": "minecraft:item",
          "name": "minecraft:carrot_on_a_stick",
          "functions": [
            {
              "function": "minecraft:set_nbt",
              "tag": "{display:{Name:'{\"text\":\"Regal Sceptre\",\"color\":\"green\",\"bold\":false,\"italic\":false}'},Unbreakable:1b,Damage:1,CustomModelData:6164003,Enchantments:[{}]}"
            },
            {
              "function": "minecraft:set_count",
              "count": 1
            }
          ],
          "conditions": [
            {
              "condition": "minecraft:random_chance",
              "chance": 0.5
            }
          ]
        },
        {
          "type": "minecraft:item",
          "name": "minecraft:iron_sword",
          "functions": [
            {
              "function": "minecraft:set_count",
              "count": 1
            },
            {
              "function": "minecraft:set_nbt",
              "tag": "{display:{Name:'{\"text\":\"Royal Rapier\",\"color\":\"green\",\"bold\":false,\"italic\":false}'},Damage:1,CustomModelData:6164002,Enchantments:[{id:\"minecraft:sharpness\",lvl:5s},{id:\"minecraft:knockback\",lvl:3s},{id:\"minecraft:sweeping\",lvl:10s},{id:\"minecraft:unbreaking\",lvl:3s},{id:\"minecraft:mending\",lvl:1s}],AttributeModifiers:[{AttributeName:\"generic.max_health\",Name:\"generic.max_health\",Amount:5,Operation:0,UUID:[I;202304855,-1108455994,-1094019280,-27226647],Slot:\"mainhand\"},{AttributeName:\"generic.movement_speed\",Name:\"generic.movement_speed\",Amount:-0.3,Operation:1,UUID:[I;-422253787,-634302744,-1197393850,1830845055],Slot:\"mainhand\"},{AttributeName:\"generic.attack_damage\",Name:\"generic.attack_damage\",Amount:30,Operation:0,UUID:[I;94443295,1459962489,-1724078314,-1809296898],Slot:\"mainhand\"},{AttributeName:\"generic.attack_speed\",Name:\"generic.attack_speed\",Amount:3,Operation:2,UUID:[I;2128750204,-1224718988,-1486598868,-2127604010],Slot:\"mainhand\"}]}"
            }
          ],
          "conditions": [
            {
              "condition": "minecraft:random_chance",
              "chance": 0.5
            }
          ]
        },
        {
          "type": "minecraft:item",
          "name": "minecraft:carrot_on_a_stick",
          "functions": [
            {
              "function": "minecraft:set_nbt",
              "tag": "{display:{Name:'{\"text\":\"Queen\\'s Satchel\",\"color\":\"green\",\"bold\":false,\"italic\":false}'},CustomModelData:6164006,Enchantments:[{}]}"
            },
            {
              "function": "minecraft:set_count",
              "count": 1
            }
          ],
          "conditions": [
            {
              "condition": "minecraft:random_chance",
              "chance": 0.5
            }
          ]
        }
      ]
    }
  ]
}
